dawgie/__init__.py
dawgie/context.py
dawgie/security.py
dawgie/types.py
dawgie/db/__init__.py
dawgie/db/lockview.py
dawgie/db/post.py
dawgie/db/test.py
dawgie/db/testdata.py
dawgie/db/shelve/__init__.py
dawgie/db/shelve/comms.py
dawgie/db/shelve/enums.py
dawgie/db/shelve/model.py
dawgie/db/shelve/state.py
dawgie/db/shelve/util.py
dawgie/db/tools/__init__.py
dawgie/db/tools/dbsinfo.py
dawgie/db/tools/extract.py
dawgie/db/tools/inter.py
dawgie/db/tools/list.py
dawgie/db/tools/post2shelve.py
dawgie/db/tools/purge.py
dawgie/db/tools/sandbox.py
dawgie/db/tools/util.py
dawgie/db/tools/worm.py
dawgie/db/util/__init__.py
dawgie/db/util/wraps.py
dawgie/de/__init__.py
dawgie/de/html.py
dawgie/fe/__init__.py
dawgie/fe/__main__.py
dawgie/fe/app.py
dawgie/fe/basis.py
dawgie/fe/requirements.txt
dawgie/fe/submit.py
dawgie/fe/svrender.py
dawgie/fe/fonts/open-sans-v13-latin-300.eot
dawgie/fe/fonts/open-sans-v13-latin-300.svg
dawgie/fe/fonts/open-sans-v13-latin-300.ttf
dawgie/fe/fonts/open-sans-v13-latin-300.woff
dawgie/fe/fonts/open-sans-v13-latin-300.woff2
dawgie/fe/fonts/open-sans-v13-latin-700.eot
dawgie/fe/fonts/open-sans-v13-latin-700.svg
dawgie/fe/fonts/open-sans-v13-latin-700.ttf
dawgie/fe/fonts/open-sans-v13-latin-700.woff
dawgie/fe/fonts/open-sans-v13-latin-700.woff2
dawgie/fe/fonts/open-sans-v13-latin-regular.eot
dawgie/fe/fonts/open-sans-v13-latin-regular.svg
dawgie/fe/fonts/open-sans-v13-latin-regular.ttf
dawgie/fe/fonts/open-sans-v13-latin-regular.woff
dawgie/fe/fonts/open-sans-v13-latin-regular.woff2
dawgie/fe/fonts/bootstrap/glyphicons-halflings-regular.eot
dawgie/fe/fonts/bootstrap/glyphicons-halflings-regular.svg
dawgie/fe/fonts/bootstrap/glyphicons-halflings-regular.ttf
dawgie/fe/fonts/bootstrap/glyphicons-halflings-regular.woff
dawgie/fe/fonts/bootstrap/glyphicons-halflings-regular.woff2
dawgie/fe/images/loading.gif
dawgie/fe/javascripts/algorithms_table.js
dawgie/fe/javascripts/application.js
dawgie/fe/javascripts/db.js
dawgie/fe/javascripts/schedule.js
dawgie-2.0.2.dist-info/METADATA
dawgie-2.0.2.dist-info/WHEEL
dawgie-2.0.2.dist-info/top_level.txt
dawgie-2.0.2.dist-info/RECORD
