Metadata-Version: 2.4
Name: dawgie
Version: 2.0.2
Summary: Data and Algorithm Work-flow Generation, Introspection, and Execution (DAWGIE)
Home-page: https://github.com/al-niessner/DAWGIE
Author: Al Niessner
Author-email: Al.Niessner@jpl.nasa.gov
License: see LICENSE file for details
Keywords: adaptive pipeline
Classifier: Programming Language :: Python :: 3
Classifier: Programming Language :: Python :: 3.10
Classifier: Programming Language :: Python :: 3.12
Classifier: Operating System :: OS Independent
Classifier: License :: Free To Use But Restricted
Classifier: Development Status :: 5 - Production/Stable
Requires-Python: >=3.10
Requires-Dist: bokeh>=1.2
Requires-Dist: boto3>=1.7.80
Requires-Dist: cryptography>=2.1.4
Requires-Dist: dawgie-pydot3==1.0.11
Requires-Dist: GitPython>=2.1.11
Requires-Dist: matplotlib>=2.1.1
Requires-Dist: progressbar2
Requires-Dist: psycopg>=3.2.12
Requires-Dist: psycopg-binary>=3.2.12
Requires-Dist: pyparsing>=2.4.7
Requires-Dist: pyOpenSSL>=19.1.0
Requires-Dist: python-gnupg==0.4.9
Requires-Dist: service_identity
Requires-Dist: requests>=2.20.0
Requires-Dist: transitions
Requires-Dist: twisted>=24.3.0
Dynamic: author
Dynamic: author-email
Dynamic: classifier
Dynamic: description
Dynamic: description-content-type
Dynamic: home-page
Dynamic: keywords
Dynamic: license
Dynamic: requires-dist
Dynamic: requires-python
Dynamic: summary
